bdast/__init__.py
bdast/__main__.py
bdast/bdast_v1.py
bdast/bdast_v2.py
bdast/cli.py
bdast/exception.py
bdast-0.5.3.dist-info/licenses/LICENSE
bdast-0.5.3.dist-info/METADATA
bdast-0.5.3.dist-info/WHEEL
bdast-0.5.3.dist-info/entry_points.txt
bdast-0.5.3.dist-info/top_level.txt
bdast-0.5.3.dist-info/RECORD
