Metadata-Version: 2.4
Name: bdast
Version: 0.5.3
Summary: Build and Deployment Assistant
Home-page: https://github.com/archmachina/bdast
Download-URL: https://pypi.org/project/bdast/
Author: Jesse Reichman
License: MIT
Keywords: Build,Deployment,Assistant
License-File: LICENSE
Requires-Dist: requests>=2.32.3
Requires-Dist: PyYAML>=6.0.1
Requires-Dist: obslib>=0.7.1
Dynamic: author
Dynamic: description
Dynamic: description-content-type
Dynamic: download-url
Dynamic: home-page
Dynamic: keywords
Dynamic: license
Dynamic: license-file
Dynamic: requires-dist
Dynamic: summary
